ScrapPyJS/__init__.py
ScrapPyJS/scrappy.py
ScrapPyJS-1.1.0.dist-info/LICENSE
ScrapPyJS-1.1.0.dist-info/METADATA
ScrapPyJS-1.1.0.dist-info/WHEEL
ScrapPyJS-1.1.0.dist-info/top_level.txt
ScrapPyJS-1.1.0.dist-info/RECORD
