Metadata-Version: 2.1
Name: ScrapPyJS
Version: 1.1.0
Summary: An easy to use web scrapping library via JS scripts
Author: Hind Sagar Biswas
Author-email: <hindsbhk@gmail.com>
Keywords: python,web scrapping,scrape data
Classifier: Development Status :: 5 - Production/Stable
Classifier: Intended Audience :: Developers
Classifier: Programming Language :: Python :: 3
Classifier: Operating System :: Unix
Classifier: Operating System :: MacOS :: MacOS X
Classifier: Operating System :: Microsoft :: Windows
License-File: LICENSE
Requires-Dist: selenium
Requires-Dist: tqdm
Provides-Extra: dev
Requires-Dist: pytest (>=7.0) ; extra == 'dev'
Requires-Dist: twine (>=4.0.2) ; extra == 'dev'
